MANIFEST.in
README.rst
setup.py
django_http_logs/__init__.py
django_http_logs/admin.py
django_http_logs/apps.py
django_http_logs/models.py
django_http_logs/serializers.py
django_http_logs/tasks.py
django_http_logs/tests.py
django_http_logs/urls.py
django_http_logs/views.py
django_http_logs.egg-info/PKG-INFO
django_http_logs.egg-info/SOURCES.txt
django_http_logs.egg-info/dependency_links.txt
django_http_logs.egg-info/top_level.txt
django_http_logs/management/__init__.py
django_http_logs/management/__pycache__/__init__.cpython-36.pyc
django_http_logs/management/commands/__init__.py
django_http_logs/management/commands/clear_http_logs.py
django_http_logs/migrations/0001_initial.py
django_http_logs/migrations/0002_auto_20201119_0922.py
django_http_logs/migrations/0003_auto_20201119_1039.py
django_http_logs/migrations/0004_auto_20201119_1045.py
django_http_logs/migrations/0005_auto_20201119_1047.py
django_http_logs/migrations/0006_auto_20201119_1209.py
django_http_logs/migrations/__init__.py
django_http_logs/migrations/__pycache__/0001_initial.cpython-36.pyc
django_http_logs/migrations/__pycache__/0002_auto_20201119_0922.cpython-36.pyc
django_http_logs/migrations/__pycache__/0003_auto_20201119_1039.cpython-36.pyc
django_http_logs/migrations/__pycache__/0004_auto_20201119_1045.cpython-36.pyc
django_http_logs/migrations/__pycache__/0005_auto_20201119_1047.cpython-36.pyc
django_http_logs/migrations/__pycache__/0006_auto_20201119_1209.cpython-36.pyc
django_http_logs/migrations/__pycache__/__init__.cpython-36.pyc