Metadata-Version: 1.0
Name: django-http-logs
Version: 1.0.7
Summary: django logs 
Home-page: UNKNOWN
Author: bigpangl
Author-email: bigpangl@163.com
License: BSD License
Platform: UNKNOWN
